<?xml version="1.0" encoding="UTF-8" standalone="no"?>
<profiles version="13">
    <profile kind="CodeFormatterProfile" name="CustomFormatter" version="13">
        <!-- Use spaces, size = 4 -->
        <setting id="org.eclipse.jdt.core.formatter.tabulation.char" value="space"/>
        <setting id="org.eclipse.jdt.core.formatter.tabulation.size" value="4"/>
        <setting id="org.eclipse.jdt.core.formatter.indentation.size" value="4"/>

        <!-- Switch / case alignment -->
        <setting id="org.eclipse.jdt.core.formatter.indent_switchstatements_compare_to_switch" value="false"/>
        <setting id="org.eclipse.jdt.core.formatter.indent_case_statements_compare_to_switch" value="false"/>

        <!-- Optional: braces on same line -->
        <setting id="org.eclipse.jdt.core.formatter.brace_position_for_switch" value="end_of_line"/>
    </profile>
</profiles>
